erd_python/__init__.py
erd_python/cli.py
erd_python/erd.py
erd_python/models.py
erd_python/parser.py
erd_python/render.py
erd_python/templates.py
erd_python-0.6.2.dist-info/LICENSE
erd_python-0.6.2.dist-info/WHEEL
erd_python-0.6.2.dist-info/METADATA
erd_python-0.6.2.dist-info/RECORD
