Metadata-Version: 2.1
Name: erd-python
Version: 0.6.2
Summary: Generate ERD diagrams using python
License: MIT
Author: Datateer
Author-email: dev@datateer.com
Requires-Python: >=3.8,<4.0
Classifier: License :: OSI Approved :: MIT License
Classifier: Programming Language :: Python :: 3
Classifier: Programming Language :: Python :: 3.10
Classifier: Programming Language :: Python :: 3.8
Classifier: Programming Language :: Python :: 3.9
Requires-Dist: click (>=7.0)
Requires-Dist: ply (>=3.11)
Requires-Dist: pygraphviz (>=1.6)
